deprecation_factory/__init__.py
deprecation_factory/_version.py
deprecation_factory/default_parameter_change.py
deprecation_factory/docscrape.py
deprecation_factory/kwonly_change.py
deprecation_factory/merge_docstrings.py
deprecation_factory/tests/__init__.py
deprecation_factory/tests/test_default_parameter_change.py
deprecation_factory/tests/test_default_parameter_change_numpydoc.py
deprecation_factory/tests/test_kwonly_deprecation.py
deprecation_factory-0.2.4.dist-info/LICENSE.txt
deprecation_factory-0.2.4.dist-info/METADATA
deprecation_factory-0.2.4.dist-info/RECORD
deprecation_factory-0.2.4.dist-info/WHEEL
deprecation_factory-0.2.4.dist-info/top_level.txt
