Metadata-Version: 2.1
Name: deprecation-factory
Version: 0.2.4
Summary: Python deprecation factory ensuring useful warnings and docstrings for different deprecations.
Home-page: https://github.com/hmaarrfk/deprecation_factory
Author: Mark Harfouche
Author-email: mark.harfouche@gmail.com
License: BSD license
Keywords: deprecation_factory
Platform: UNKNOWN
Classifier: Development Status :: 2 - Pre-Alpha
Classifier: Intended Audience :: Developers
Classifier: License :: OSI Approved :: BSD License
Classifier: Natural Language :: English
Classifier: Programming Language :: Python :: 3
Classifier: Programming Language :: Python :: 3.5
Classifier: Programming Language :: Python :: 3.6
Classifier: Programming Language :: Python :: 3.7
